ordeq_files/__init__.py
ordeq_files/_version.py
ordeq_files/bytes.py
ordeq_files/bz2.py
ordeq_files/csv.py
ordeq_files/glob.py
ordeq_files/gzip.py
ordeq_files/json.py
ordeq_files/pickle.py
ordeq_files/py.typed
ordeq_files/text.py
ordeq_files/text_lines_stream.py
ordeq_files-1.1.3.dist-info/licenses/LICENSE
ordeq_files-1.1.3.dist-info/METADATA
ordeq_files-1.1.3.dist-info/WHEEL
ordeq_files-1.1.3.dist-info/top_level.txt
ordeq_files-1.1.3.dist-info/RECORD
