Metadata-Version: 2.4
Name: ordeq_files
Version: 1.1.3
Summary: A collection of file IOs for Ordeq (e.g. Text, CSV, JSON, Pickle)
Author: Niels Neerhoff, Simon Brugman
Maintainer: Niels Neerhoff, Simon Brugman
License-Expression: MIT
Requires-Python: >=3.10
License-File: LICENSE
Requires-Dist: ordeq>=1.4.0
Dynamic: license-file
